{"cameraMode":{"drawMode":0,"name":"Shaded","section":"Shading Mode"},"sceneLighting":true,"audioPlay":false,"sceneViewState":{"m_AlwaysRefresh":false,"showFog":true,"showSkybox":true,"showFlares":true,"showImageEffects":true,"showParticleSystems":true,"showVisualEffectGraphs":true,"m_FxEnabled":true},"in2DMode":false,"pivot":{"x":-0.9232780933380127,"y":8.622318267822266,"z":0.4231722950935364},"rotation":{"x":-0.1629205346107483,"y":0.043493274599313739,"z":-0.007188945543020964,"w":-0.9856598973274231},"size":10.0,"orthographic":false}